django_pwned_passwords/__init__.py
django_pwned_passwords/apps.py
django_pwned_passwords/password_validation.py
django_pwned_passwords-4.1.0.dist-info/DESCRIPTION.rst
django_pwned_passwords-4.1.0.dist-info/METADATA
django_pwned_passwords-4.1.0.dist-info/RECORD
django_pwned_passwords-4.1.0.dist-info/WHEEL
django_pwned_passwords-4.1.0.dist-info/metadata.json
django_pwned_passwords-4.1.0.dist-info/top_level.txt
