Metadata-Version: 2.0
Name: django-pwned-passwords
Version: 4.1.0
Summary: A Django password validator that checks Troy Hunt's PWNED Passwords API to see if a password has been involved in a major security breach before.
Home-page: https://github.com/jamiecounsell/django-pwned-passwords
Author: Jamie Counsell
Author-email: jamiecounsell@me.com
License: MIT
Keywords: django-pwned-passwords
Platform: UNKNOWN
Classifier: Development Status :: 3 - Alpha
Classifier: Framework :: Django
Classifier: Framework :: Django :: 1.9
Classifier: Framework :: Django :: 1.10
Classifier: Framework :: Django :: 1.11
Classifier: Framework :: Django :: 2.0
Classifier: Framework :: Django :: 2.1
Classifier: Intended Audience :: Developers
Classifier: License :: OSI Approved :: BSD License
Classifier: Natural Language :: English
Classifier: Programming Language :: Python :: 2
Classifier: Programming Language :: Python :: 2.7
Classifier: Programming Language :: Python :: 3
Classifier: Programming Language :: Python :: 3.5
Classifier: Programming Language :: Python :: 3.6
Classifier: Programming Language :: Python :: 3.7
